{"v":2,"folders":[{"id":"mqp80nyuygf57","name":"3º Medicina","parentId":null,"createdAt":1782133073238},{"id":"mqp825i7ek5ti","name":"FARMA","parentId":"mqp80nyuygf57","createdAt":1782133142623},{"id":"mqp83q93ptuk2","name":"4º Medicina","parentId":null,"createdAt":1782133216167},{"id":"mqp85xak3m3iw","name":"NEUMO","parentId":"mqp83q93ptuk2","createdAt":1782133318604},{"id":"mqpb97ir418pf","name":"OFT","parentId":"mqp83q93ptuk2","createdAt":1782138510675}],"items":[{"id":"mqp878ritzwfg","name":"examen_mir_torax","folderId":"mqp85xak3m3iw","path":"data/files/mqp878ritzwfg.html","size":96642,"createdAt":1782133381610,"updatedAt":1782133381610},{"id":"mqpbbolbnhg66","name":"test_T01_oftalmologia","folderId":"mqpbb00qtl0w6","path":"data/files/mqpbbolbnhg66.html","size":59814,"createdAt":1782138627684,"updatedAt":1782138627684},{"id":"mqpbbpt3y6c91","name":"test_T02_conjuntiva","folderId":"mqpbb00qtl0w6","path":"data/files/mqpbbpt3y6c91.html","size":63833,"createdAt":1782138629034,"updatedAt":1782138629034},{"id":"mqpbbquox3gn4","name":"test_T03_cornea","folderId":"mqpbb00qtl0w6","path":"data/files/mqpbbquox3gn4.html","size":50932,"createdAt":1782138630557,"updatedAt":1782138630557},{"id":"mqpbbs0yq00yr","name":"test_T04_esclera_lagrima","folderId":"mqpbb00qtl0w6","path":"data/files/mqpbbs0yq00yr.html","size":47230,"createdAt":1782138632027,"updatedAt":1782138632027},{"id":"mqpbbt5vepnh4","name":"test_T05_dioptrio_ametropias","folderId":"mqpbb00qtl0w6","path":"data/files/mqpbbt5vepnh4.html","size":45951,"createdAt":1782138633423,"updatedAt":1782138633423},{"id":"mqpbbu8odc9qo","name":"test_T06_cristalino","folderId":"mqpbb00qtl0w6","path":"data/files/mqpbbu8odc9qo.html","size":43936,"createdAt":1782138634752,"updatedAt":1782138634752},{"id":"mqpbbv9iy4xhd","name":"test_T07_macula","folderId":"mqpbb00qtl0w6","path":"data/files/mqpbbv9iy4xhd.html","size":44051,"createdAt":1782138636105,"updatedAt":1782138636105},{"id":"mqpbbwb1owjkh","name":"test_T08_rd_rhta","folderId":"mqpbb00qtl0w6","path":"data/files/mqpbbwb1owjkh.html","size":43270,"createdAt":1782138637451,"updatedAt":1782138637451},{"id":"mqpbbxcfl74xo","name":"test_T09_oclusiones_vasculares","folderId":"mqpbb00qtl0w6","path":"data/files/mqpbbxcfl74xo.html","size":43253,"createdAt":1782138639038,"updatedAt":1782138639038},{"id":"mqpbbyklflr3g","name":"test_T10_heredodegenerativas","folderId":"mqpbb00qtl0w6","path":"data/files/mqpbbyklflr3g.html","size":40938,"createdAt":1782138640390,"updatedAt":1782138640390},{"id":"mqpbbzm32p9hf","name":"test_T11_dr_vitreorretiniana","folderId":"mqpbb00qtl0w6","path":"data/files/mqpbbzm32p9hf.html","size":42996,"createdAt":1782138641857,"updatedAt":1782138641857},{"id":"mqpbc0qzwcmmp","name":"test_T12_repaso_retina","folderId":"mqpbb00qtl0w6","path":"data/files/mqpbc0qzwcmmp.html","size":38311,"createdAt":1782138643046,"updatedAt":1782138643046},{"id":"mqpbc1nxyn8z5","name":"test_T13-14_neuroftalmologia","folderId":"mqpbb00qtl0w6","path":"data/files/mqpbc1nxyn8z5.html","size":41710,"createdAt":1782138644362,"updatedAt":1782138644362},{"id":"mqpbc2omhlsdd","name":"test_T15-16_estrabismo","folderId":"mqpbb00qtl0w6","path":"data/files/mqpbc2omhlsdd.html","size":40174,"createdAt":1782138645713,"updatedAt":1782138645713},{"id":"mqpbc3q3xavwd","name":"test_T17_glaucoma","folderId":"mqpbb00qtl0w6","path":"data/files/mqpbc3q3xavwd.html","size":40941,"createdAt":1782138647040,"updatedAt":1782138647040},{"id":"mqpbc4qwiwq7g","name":"test_T18_pediatrica","folderId":"mqpbb00qtl0w6","path":"data/files/mqpbc4qwiwq7g.html","size":42908,"createdAt":1782138648598,"updatedAt":1782138648598},{"id":"mqpbc5y645b1b","name":"test_T19_uveitis","folderId":"mqpbb00qtl0w6","path":"data/files/mqpbc5y645b1b.html","size":41102,"createdAt":1782138650014,"updatedAt":1782138650014},{"id":"mqpbc71hhsn9t","name":"test_T20_enf_sistemicas","folderId":"mqpbb00qtl0w6","path":"data/files/mqpbc71hhsn9t.html","size":42047,"createdAt":1782138651119,"updatedAt":1782138651119},{"id":"mqpbc7w8slyam","name":"test_T21_sistema_lagrimal","folderId":"mqpbb00qtl0w6","path":"data/files/mqpbc7w8slyam.html","size":38887,"createdAt":1782138652578,"updatedAt":1782138652578},{"id":"mqpbc90ssyaxg","name":"test_T22_parpados","folderId":"mqpbb00qtl0w6","path":"data/files/mqpbc90ssyaxg.html","size":41112,"createdAt":1782138653914,"updatedAt":1782138653914},{"id":"mqpbca1svsh3m","name":"test_T23_patologia_orbitaria","folderId":"mqpbb00qtl0w6","path":"data/files/mqpbca1svsh3m.html","size":41944,"createdAt":1782138655463,"updatedAt":1782138655463},{"id":"mqpbcb8x8a7xc","name":"test_T24_traumatologia","folderId":"mqpbb00qtl0w6","path":"data/files/mqpbcb8x8a7xc.html","size":40844,"createdAt":1782138657284,"updatedAt":1782138657284},{"id":"mqpbccnhmjl0k","name":"test_T25_farmacologia_preventiva","folderId":"mqpbb00qtl0w6","path":"data/files/mqpbccnhmjl0k.html","size":41447,"createdAt":1782138658700,"updatedAt":1782138658700},{"id":"mqpbcdquj8w3f","name":"test_T26_urgencias","folderId":"mqpbb00qtl0w6","path":"data/files/mqpbcdquj8w3f.html","size":43529,"createdAt":1782138660042,"updatedAt":1782138660042}],"updatedAt":1782138660042}